{
  "tcu": {
    "version": 1,
    "timestamp": 1732633755,
    "news": [
      {
        "timestamp": 1732633755,
        "details": "Thank you for playing Trombone Champ: Unflattened! We have a bunch of changes coming soon:\n\n- Tons of bug fixes!\n- Trombone calibration.\n- Support for more languages.\n- Improvements to visuals and performance.\n- Improved mixed reality (on platforms that support it).\n- New songs and environments.\n\nFind our full roadmap on <color=yellow><u>TC.FLAT2VRSTUDIOS.COM</u></color>\n<size=50%>(no you can't click this link, open it in a browser)</size>"
      }
    ]
  }
}
